cloudy_warehouses
tests
