Metadata-Version: 2.1
Name: cloudy-warehouses
Version: 0.0.4.1
Summary: Cloudy Warehouses allows for stream-lined interaction between pandas and cloud data platform providers
Home-page: https://github.com/hashmapinc/sales-and-marketing/pocs/sam-kohlleffel-poc/pandas-cloudy-extension
Author: Hashmap, Inc
Author-email: accelerators@hashmapinc.com
License: UNKNOWN
Platform: UNKNOWN
Classifier: Programming Language :: Python :: 3
Classifier: License :: OSI Approved :: Apache Software License
Classifier: Operating System :: OS Independent
Classifier: Development Status :: 3 - Alpha
Requires-Python: >=3.7
